tgmcp/__init__.py
tgmcp/__main__.py
tgmcp/authenticate.py
tgmcp/client.py
tgmcp/session_string_generator.py
tgmcp/tool_config.py
tgmcp/utils.py
tgmcp/tools/__init__.py
tgmcp/tools/admin.py
tgmcp/tools/chat.py
tgmcp/tools/contacts.py
tgmcp/tools/groups.py
tgmcp/tools/media.py
tgmcp/tools/messages.py
tgmcp/tools/profile.py
tgmcp-0.2.2.dist-info/METADATA
tgmcp-0.2.2.dist-info/WHEEL
tgmcp-0.2.2.dist-info/entry_points.txt
tgmcp-0.2.2.dist-info/top_level.txt
tgmcp-0.2.2.dist-info/RECORD
