Metadata-Version: 2.4
Name: tgmcp
Version: 0.2.2
Summary: Telegram Model Context Protocol integration
Author-email: OEvortex <koulabhay25@gmail.com>
License: MIT
Project-URL: Homepage, https://github.com/OEvortex/tgmcp
Project-URL: Bug Tracker, https://github.com/OEvortex/tgmcp/issues
Project-URL: Documentation, https://github.com/OEvortex/tgmcp/blob/main/README.md
Project-URL: Source Code, https://github.com/OEvortex/tgmcp
Project-URL: PyPI, https://pypi.org/project/tgmcp/
Keywords: telegram,mcp,ai,chat,assistant,bot
Classifier: Programming Language :: Python :: 3
Classifier: Programming Language :: Python :: 3.8
Classifier: Programming Language :: Python :: 3.9
Classifier: Programming Language :: Python :: 3.10
Classifier: Programming Language :: Python :: 3.11
Classifier: License :: OSI Approved :: MIT License
Classifier: Operating System :: OS Independent
Classifier: Development Status :: 4 - Beta
Classifier: Intended Audience :: Developers
Classifier: Topic :: Communications :: Chat
Classifier: Topic :: Software Development :: Libraries
Requires-Python: >=3.8
Requires-Dist: telethon
Requires-Dist: mcp-server
Requires-Dist: nest-asyncio
Requires-Dist: python-dotenv
